directory_mcp/__init__.py
directory_mcp/__main__.py
directory_mcp/config.py
directory_mcp/server.py
directory_mcp/server_old.py
directory_mcp/database/__init__.py
directory_mcp/database/manager.py
directory_mcp/database/migration.py
directory_mcp/database/schema.py
directory_mcp/embeddings/__init__.py
directory_mcp/embeddings/gemini.py
directory_mcp/search/__init__.py
directory_mcp/search/engine.py
directory_mcp/tools/__init__.py
directory_mcp/tools/analysis.py
directory_mcp/tools/entities.py
directory_mcp/tools/graph.py
directory_mcp/tools/relationships.py
directory_mcp/tools/search.py
directory_mcp/tools/system.py
directory_mcp/tools/entities/__init__.py
directory_mcp/tools/entities/channel.py
directory_mcp/tools/entities/company.py
directory_mcp/tools/entities/person.py
directory_mcp/tools/entities/project.py
directory_mcp/utils/__init__.py
directory_mcp/utils/resolver.py
directory_mcp/utils/serialization.py
directory_mcp-0.5.0.dist-info/licenses/LICENSE
directory_mcp-0.5.0.dist-info/METADATA
directory_mcp-0.5.0.dist-info/WHEEL
directory_mcp-0.5.0.dist-info/entry_points.txt
directory_mcp-0.5.0.dist-info/top_level.txt
directory_mcp-0.5.0.dist-info/RECORD
