Metadata-Version: 2.4
Name: directory-mcp
Version: 0.5.0
Summary: Complete entity graph MCP server with smart relationships
Author-email: Olivier Debeuf De Rijcker <olivier@markov.surge-holdings.com>
License: MIT
Project-URL: Homepage, https://github.com/markov-ai/directory-mcp
Project-URL: Documentation, https://github.com/markov-ai/directory-mcp/wiki
Project-URL: Bug Tracker, https://github.com/markov-ai/directory-mcp/issues
Keywords: mcp,claude,entity-resolution,knowledge-graph,gemini
Classifier: Development Status :: 3 - Alpha
Classifier: Intended Audience :: Developers
Classifier: License :: OSI Approved :: MIT License
Classifier: Programming Language :: Python :: 3
Classifier: Programming Language :: Python :: 3.10
Classifier: Programming Language :: Python :: 3.11
Classifier: Programming Language :: Python :: 3.12
Requires-Python: >=3.10
License-File: LICENSE
Requires-Dist: mcp>=1.9.0
Requires-Dist: aiosqlite>=0.19.0
Requires-Dist: google-generativeai>=0.3.0
Requires-Dist: numpy>=1.24.0
Requires-Dist: faiss-cpu>=1.7.4
Requires-Dist: python-dotenv>=1.0.0
Requires-Dist: click>=8.0.0
Requires-Dist: aiofiles>=23.0.0
Requires-Dist: rich>=13.0.0
Requires-Dist: python-dateutil>=2.8.0
Dynamic: license-file
